LICENSE
MANIFEST.in
README.md
setup.cfg
setup.py
kusanagi/__init__.py
kusanagi/sdk/__init__.py
kusanagi/sdk/action.py
kusanagi/sdk/actiondata.py
kusanagi/sdk/api.py
kusanagi/sdk/callee.py
kusanagi/sdk/caller.py
kusanagi/sdk/component.py
kusanagi/sdk/error.py
kusanagi/sdk/file.py
kusanagi/sdk/link.py
kusanagi/sdk/middleware.py
kusanagi/sdk/param.py
kusanagi/sdk/relation.py
kusanagi/sdk/request.py
kusanagi/sdk/response.py
kusanagi/sdk/service.py
kusanagi/sdk/servicedata.py
kusanagi/sdk/transaction.py
kusanagi/sdk/transport.py
kusanagi/sdk/lib/__init__.py
kusanagi/sdk/lib/asynchronous.py
kusanagi/sdk/lib/call.py
kusanagi/sdk/lib/cli.py
kusanagi/sdk/lib/datatypes.py
kusanagi/sdk/lib/error.py
kusanagi/sdk/lib/events.py
kusanagi/sdk/lib/formatting.py
kusanagi/sdk/lib/json.py
kusanagi/sdk/lib/logging.py
kusanagi/sdk/lib/msgpack.py
kusanagi/sdk/lib/server.py
kusanagi/sdk/lib/singleton.py
kusanagi/sdk/lib/state.py
kusanagi/sdk/lib/version.py
kusanagi/sdk/lib/payload/__init__.py
kusanagi/sdk/lib/payload/action.py
kusanagi/sdk/lib/payload/command.py
kusanagi/sdk/lib/payload/error.py
kusanagi/sdk/lib/payload/file.py
kusanagi/sdk/lib/payload/mapping.py
kusanagi/sdk/lib/payload/ns.py
kusanagi/sdk/lib/payload/param.py
kusanagi/sdk/lib/payload/reply.py
kusanagi/sdk/lib/payload/request.py
kusanagi/sdk/lib/payload/response.py
kusanagi/sdk/lib/payload/service.py
kusanagi/sdk/lib/payload/transport.py
kusanagi/sdk/lib/payload/utils.py
kusanagi_sdk_python.egg-info/PKG-INFO
kusanagi_sdk_python.egg-info/SOURCES.txt
kusanagi_sdk_python.egg-info/dependency_links.txt
kusanagi_sdk_python.egg-info/namespace_packages.txt
kusanagi_sdk_python.egg-info/requires.txt
kusanagi_sdk_python.egg-info/top_level.txt
kusanagi_sdk_python.egg-info/zip-safe