Metadata-Version: 1.1
Name: kusanagi-sdk-python
Version: 2.1.0
Summary: Python SDK for the KUSANAGI™ framework
Home-page: http://kusanagi.io/
Author: Jerónimo Albi
Author-email: jeronimo.albi@kusanagi.io
License: MIT
Download-URL: https://github.com/kusanagi/kusanagi-sdk-python/releases
Platform: POSIX
Classifier: Intended Audience :: Developers
Classifier: Programming Language :: Python :: 3.7
Classifier: Programming Language :: Python :: 3.8
Classifier: Operating System :: POSIX :: Linux
Classifier: Topic :: Software Development :: Libraries :: Application Frameworks
Classifier: Topic :: Software Development :: Libraries :: Python Modules
Classifier: Topic :: System :: Networking
